air_labs_helpers/__init__.py
air_labs_helpers/air_labs_plugins_helper.py
air_labs_helpers-0.1.1.dist-info/METADATA
air_labs_helpers-0.1.1.dist-info/WHEEL
air_labs_helpers-0.1.1.dist-info/RECORD
