Metadata-Version: 2.4
Name: air-labs-helpers
Version: 0.1.1
Summary: Shared helper utilities for Airflow Xtra plugins.
Author: Rahul Rajasekharan
License: MIT
Requires-Python: >=3.9
